biostrings-0.0.2.dist-info/RECORD
biostrings-0.0.2.dist-info/WHEEL
biostrings-0.0.2.dist-info/top_level.txt
biostrings-0.0.2.dist-info/METADATA
biostrings-0.0.2.dist-info/licenses/LICENSE.txt
biostrings/__init__.py
biostrings/dnastring.py
biostrings/utils.py
biostrings/dnastringset.py
biostrings/lib_biostrings.cpython-39-darwin.so
