Metadata-Version: 2.4
Name: biostrings
Version: 0.0.2
Summary: Efficient manipulation of genomic sequences
Home-page: https://github.com/pyscaffold/pyscaffold/
Author: Jayaram Kancherla
Author-email: jayaram.kancherla@gmail.com
License: MIT
Project-URL: Documentation, https://github.com/BiocPy/biostrings
Project-URL: Source, https://github.com/BiocPy/biostrings
Platform: any
Classifier: Development Status :: 4 - Beta
Classifier: Programming Language :: Python
Requires-Python: >=3.9
License-File: LICENSE.txt
Requires-Dist: importlib-metadata; python_version < "3.8"
Requires-Dist: iranges
Requires-Dist: numpy
Requires-Dist: biocutils>=0.3.3
Provides-Extra: testing
Requires-Dist: setuptools; extra == "testing"
Requires-Dist: pytest; extra == "testing"
Requires-Dist: pytest-cov; extra == "testing"
Dynamic: license-file
